<?xml version="1.0" ?>
<annotation>
<folder>-80</folder>
<filename>313.jpg</filename>
<path>/home/w/zxl/-80/313.jpg</path>
<source>
    <database>Unknown</database>
</source>
<size>
    <width>2560</width>
    <height>1922</height>
    <depth>3</depth>
</size>

<segmented>0</segmented>
    <object>
    <name>depth:-80</name>
    <pose>Unspecified</pose>
    <truncated>0</truncated>
    <difficult>0</difficult>
    <bndbox>
        <xmin>779</xmin>
        <ymin>109</ymin>
        <xmax>980</xmax>
        <ymax>313</ymax>
    </bndbox>
</object>
    <object>
    <name>depth:-80</name>
    <pose>Unspecified</pose>
    <truncated>0</truncated>
    <difficult>0</difficult>
    <bndbox>
        <xmin>1064</xmin>
        <ymin>40</ymin>
        <xmax>1256</xmax>
        <ymax>226</ymax>
    </bndbox>
</object>
    <object>
    <name>depth:-80</name>
    <pose>Unspecified</pose>
    <truncated>0</truncated>
    <difficult>0</difficult>
    <bndbox>
        <xmin>728</xmin>
        <ymin>806</ymin>
        <xmax>935</xmax>
        <ymax>1007</ymax>
    </bndbox>
</object>
    <object>
    <name>depth:-80</name>
    <pose>Unspecified</pose>
    <truncated>0</truncated>
    <difficult>0</difficult>
    <bndbox>
        <xmin>663</xmin>
        <ymin>972</ymin>
        <xmax>864</xmax>
        <ymax>1158</ymax>
    </bndbox>
</object>
    <object>
    <name>depth:-80</name>
    <pose>Unspecified</pose>
    <truncated>0</truncated>
    <difficult>0</difficult>
    <bndbox>
        <xmin>932</xmin>
        <ymin>1600</ymin>
        <xmax>1151</xmax>
        <ymax>1795</ymax>
    </bndbox>
</object>
    <object>
    <name>depth:-80</name>
    <pose>Unspecified</pose>
    <truncated>0</truncated>
    <difficult>0</difficult>
    <bndbox>
        <xmin>382</xmin>
        <ymin>1527</ymin>
        <xmax>596</xmax>
        <ymax>1743</ymax>
    </bndbox>
</object>
    <object>
    <name>depth:-80</name>
    <pose>Unspecified</pose>
    <truncated>0</truncated>
    <difficult>0</difficult>
    <bndbox>
        <xmin>468</xmin>
        <ymin>1591</ymin>
        <xmax>685</xmax>
        <ymax>1786</ymax>
    </bndbox>
</object>
    <object>
    <name>depth:-80</name>
    <pose>Unspecified</pose>
    <truncated>0</truncated>
    <difficult>0</difficult>
    <bndbox>
        <xmin>1983</xmin>
        <ymin>1157</ymin>
        <xmax>2190</xmax>
        <ymax>1352</ymax>
    </bndbox>
</object>
    <object>
    <name>depth:-80</name>
    <pose>Unspecified</pose>
    <truncated>0</truncated>
    <difficult>0</difficult>
    <bndbox>
        <xmin>2013</xmin>
        <ymin>1481</ymin>
        <xmax>2196</xmax>
        <ymax>1683</ymax>
    </bndbox>
</object>
    <object>
    <name>depth:-80</name>
    <pose>Unspecified</pose>
    <truncated>0</truncated>
    <difficult>0</difficult>
    <bndbox>
        <xmin>1493</xmin>
        <ymin>1379</ymin>
        <xmax>1683</xmax>
        <ymax>1566</ymax>
    </bndbox>
</object>
    <object>
    <name>depth:-80</name>
    <pose>Unspecified</pose>
    <truncated>0</truncated>
    <difficult>0</difficult>
    <bndbox>
        <xmin>1591</xmin>
        <ymin>1426</ymin>
        <xmax>1780</xmax>
        <ymax>1601</ymax>
    </bndbox>
</object>
    <object>
    <name>depth:-80</name>
    <pose>Unspecified</pose>
    <truncated>0</truncated>
    <difficult>0</difficult>
    <bndbox>
        <xmin>1512</xmin>
        <ymin>1536</ymin>
        <xmax>1704</xmax>
        <ymax>1713</ymax>
    </bndbox>
</object>
    <object>
    <name>depth:-80</name>
    <pose>Unspecified</pose>
    <truncated>0</truncated>
    <difficult>0</difficult>
    <bndbox>
        <xmin>2325</xmin>
        <ymin>1373</ymin>
        <xmax>2518</xmax>
        <ymax>1551</ymax>
    </bndbox>
</object>
    <object>
    <name>depth:-80</name>
    <pose>Unspecified</pose>
    <truncated>0</truncated>
    <difficult>0</difficult>
    <bndbox>
        <xmin>2304</xmin>
        <ymin>938</ymin>
        <xmax>2518</xmax>
        <ymax>1127</ymax>
    </bndbox>
</object>
    <object>
    <name>depth:-80</name>
    <pose>Unspecified</pose>
    <truncated>0</truncated>
    <difficult>0</difficult>
    <bndbox>
        <xmin>2372</xmin>
        <ymin>690</ymin>
        <xmax>2586</xmax>
        <ymax>906</ymax>
    </bndbox>
</object>
    <object>
    <name>depth:-80</name>
    <pose>Unspecified</pose>
    <truncated>0</truncated>
    <difficult>0</difficult>
    <bndbox>
        <xmin>2121</xmin>
        <ymin>-1</ymin>
        <xmax>2322</xmax>
        <ymax>181</ymax>
    </bndbox>
</object>
    <object>
    <name>depth:-80</name>
    <pose>Unspecified</pose>
    <truncated>0</truncated>
    <difficult>0</difficult>
    <bndbox>
        <xmin>1596</xmin>
        <ymin>4</ymin>
        <xmax>1800</xmax>
        <ymax>193</ymax>
    </bndbox>
</object>
</annotation>
