<?xml version="1.0" ?>
<annotation>
<folder>20</folder>
<filename>379.jpg</filename>
<path>/home/w/zxl/20/379.jpg</path>
<source>
    <database>Unknown</database>
</source>
<size>
    <width>2560</width>
    <height>1922</height>
    <depth>3</depth>
</size>

<segmented>0</segmented>
    <object>
    <name>depth:20</name>
    <pose>Unspecified</pose>
    <truncated>0</truncated>
    <difficult>0</difficult>
    <bndbox>
        <xmin>193</xmin>
        <ymin>31</ymin>
        <xmax>364</xmax>
        <ymax>211</ymax>
    </bndbox>
</object>
    <object>
    <name>depth:20</name>
    <pose>Unspecified</pose>
    <truncated>0</truncated>
    <difficult>0</difficult>
    <bndbox>
        <xmin>340</xmin>
        <ymin>1202</ymin>
        <xmax>548</xmax>
        <ymax>1394</ymax>
    </bndbox>
</object>
    <object>
    <name>depth:20</name>
    <pose>Unspecified</pose>
    <truncated>0</truncated>
    <difficult>0</difficult>
    <bndbox>
        <xmin>629</xmin>
        <ymin>1145</ymin>
        <xmax>821</xmax>
        <ymax>1334</ymax>
    </bndbox>
</object>
    <object>
    <name>depth:20</name>
    <pose>Unspecified</pose>
    <truncated>0</truncated>
    <difficult>0</difficult>
    <bndbox>
        <xmin>1031</xmin>
        <ymin>1310</ymin>
        <xmax>1229</xmax>
        <ymax>1487</ymax>
    </bndbox>
</object>
    <object>
    <name>depth:20</name>
    <pose>Unspecified</pose>
    <truncated>0</truncated>
    <difficult>0</difficult>
    <bndbox>
        <xmin>1542</xmin>
        <ymin>493</ymin>
        <xmax>1734</xmax>
        <ymax>689</ymax>
    </bndbox>
</object>
    <object>
    <name>depth:20</name>
    <pose>Unspecified</pose>
    <truncated>0</truncated>
    <difficult>0</difficult>
    <bndbox>
        <xmin>1917</xmin>
        <ymin>430</ymin>
        <xmax>2103</xmax>
        <ymax>632</ymax>
    </bndbox>
</object>
</annotation>
