<?xml version="1.0" ?>
<annotation>
<folder>40</folder>
<filename>433.jpg</filename>
<path>/home/w/zxl/40/433.jpg</path>
<source>
    <database>Unknown</database>
</source>
<size>
    <width>2560</width>
    <height>1922</height>
    <depth>3</depth>
</size>

<segmented>0</segmented>
    <object>
    <name>depth:40</name>
    <pose>Unspecified</pose>
    <truncated>0</truncated>
    <difficult>0</difficult>
    <bndbox>
        <xmin>148</xmin>
        <ymin>7</ymin>
        <xmax>376</xmax>
        <ymax>193</ymax>
    </bndbox>
</object>
    <object>
    <name>depth:40</name>
    <pose>Unspecified</pose>
    <truncated>0</truncated>
    <difficult>0</difficult>
    <bndbox>
        <xmin>-37</xmin>
        <ymin>578</ymin>
        <xmax>124</xmax>
        <ymax>770</ymax>
    </bndbox>
</object>
    <object>
    <name>depth:40</name>
    <pose>Unspecified</pose>
    <truncated>0</truncated>
    <difficult>0</difficult>
    <bndbox>
        <xmin>325</xmin>
        <ymin>1175</ymin>
        <xmax>533</xmax>
        <ymax>1370</ymax>
    </bndbox>
</object>
    <object>
    <name>depth:40</name>
    <pose>Unspecified</pose>
    <truncated>0</truncated>
    <difficult>0</difficult>
    <bndbox>
        <xmin>593</xmin>
        <ymin>1112</ymin>
        <xmax>836</xmax>
        <ymax>1334</ymax>
    </bndbox>
</object>
    <object>
    <name>depth:40</name>
    <pose>Unspecified</pose>
    <truncated>0</truncated>
    <difficult>0</difficult>
    <bndbox>
        <xmin>1004</xmin>
        <ymin>1265</ymin>
        <xmax>1223</xmax>
        <ymax>1478</ymax>
    </bndbox>
</object>
    <object>
    <name>depth:40</name>
    <pose>Unspecified</pose>
    <truncated>0</truncated>
    <difficult>0</difficult>
    <bndbox>
        <xmin>1518</xmin>
        <ymin>478</ymin>
        <xmax>1737</xmax>
        <ymax>662</ymax>
    </bndbox>
</object>
    <object>
    <name>depth:40</name>
    <pose>Unspecified</pose>
    <truncated>0</truncated>
    <difficult>0</difficult>
    <bndbox>
        <xmin>1914</xmin>
        <ymin>406</ymin>
        <xmax>2115</xmax>
        <ymax>614</ymax>
    </bndbox>
</object>
    <object>
    <name>depth:40</name>
    <pose>Unspecified</pose>
    <truncated>0</truncated>
    <difficult>0</difficult>
    <bndbox>
        <xmin>1878</xmin>
        <ymin>695</ymin>
        <xmax>2082</xmax>
        <ymax>899</ymax>
    </bndbox>
</object>
</annotation>
