<?xml version="1.0" ?>
<annotation>
<folder>24</folder>
<filename>205.png</filename>
<path>/home/w/zxl/24/205.png</path>
<source>
    <database>Unknown</database>
</source>
<size>
    <width>1280</width>
    <height>961</height>
    <depth>3</depth>
</size>

<segmented>0</segmented>
    <object>
    <name>depth:24</name>
    <pose>Unspecified</pose>
    <truncated>0</truncated>
    <difficult>0</difficult>
    <bndbox>
        <xmin>339</xmin>
        <ymin>182</ymin>
        <xmax>492</xmax>
        <ymax>317</ymax>
    </bndbox>
</object>
    <object>
    <name>depth:24</name>
    <pose>Unspecified</pose>
    <truncated>0</truncated>
    <difficult>0</difficult>
    <bndbox>
        <xmin>600</xmin>
        <ymin>863</ymin>
        <xmax>751</xmax>
        <ymax>971</ymax>
    </bndbox>
</object>
    <object>
    <name>depth:24</name>
    <pose>Unspecified</pose>
    <truncated>0</truncated>
    <difficult>0</difficult>
    <bndbox>
        <xmin>1133</xmin>
        <ymin>728</ymin>
        <xmax>1277</xmax>
        <ymax>860</ymax>
    </bndbox>
</object>
</annotation>
