<?xml version="1.0" ?>
<annotation>
<folder>20</folder>
<filename>30.jpg</filename>
<path>/home/w/zxl/fuyou/zong/20/30.jpg</path>
<source>
    <database>Unknown</database>
</source>
<size>
    <width>800</width>
    <height>800</height>
    <depth>3</depth>
</size>

<segmented>0</segmented>
    <object>
    <name>depth:20</name>
    <pose>Unspecified</pose>
    <truncated>0</truncated>
    <difficult>0</difficult>
    <bndbox>
        <xmin>412</xmin>
        <ymin>434</ymin>
        <xmax>730</xmax>
        <ymax>632</ymax>
    </bndbox>
</object>
</annotation>
